odoo9_addon_project_task_default_stage-9.0.1.0.0.99.dev21-py2.7-nspkg.pth
odoo9_addon_project_task_default_stage-9.0.1.0.0.99.dev21.dist-info/DESCRIPTION.rst
odoo9_addon_project_task_default_stage-9.0.1.0.0.99.dev21.dist-info/METADATA
odoo9_addon_project_task_default_stage-9.0.1.0.0.99.dev21.dist-info/RECORD
odoo9_addon_project_task_default_stage-9.0.1.0.0.99.dev21.dist-info/WHEEL
odoo9_addon_project_task_default_stage-9.0.1.0.0.99.dev21.dist-info/metadata.json
odoo9_addon_project_task_default_stage-9.0.1.0.0.99.dev21.dist-info/namespace_packages.txt
odoo9_addon_project_task_default_stage-9.0.1.0.0.99.dev21.dist-info/top_level.txt
odoo_addons/project_task_default_stage/README.rst
odoo_addons/project_task_default_stage/__init__.py
odoo_addons/project_task_default_stage/__openerp__.py
odoo_addons/project_task_default_stage/data/project_data.xml
odoo_addons/project_task_default_stage/i18n/bg.po
odoo_addons/project_task_default_stage/i18n/ca.po
odoo_addons/project_task_default_stage/i18n/de.po
odoo_addons/project_task_default_stage/i18n/es.po
odoo_addons/project_task_default_stage/i18n/es_MX.po
odoo_addons/project_task_default_stage/i18n/fi.po
odoo_addons/project_task_default_stage/i18n/fr.po
odoo_addons/project_task_default_stage/i18n/hr.po
odoo_addons/project_task_default_stage/i18n/id.po
odoo_addons/project_task_default_stage/i18n/it.po
odoo_addons/project_task_default_stage/i18n/nb.po
odoo_addons/project_task_default_stage/i18n/nl.po
odoo_addons/project_task_default_stage/i18n/project_task_default_stage.pot
odoo_addons/project_task_default_stage/i18n/pt.po
odoo_addons/project_task_default_stage/i18n/pt_BR.po
odoo_addons/project_task_default_stage/i18n/pt_PT.po
odoo_addons/project_task_default_stage/i18n/ru.po
odoo_addons/project_task_default_stage/i18n/sk.po
odoo_addons/project_task_default_stage/i18n/sl.po
odoo_addons/project_task_default_stage/i18n/tr_TR.po
odoo_addons/project_task_default_stage/i18n/zh_CN.po
odoo_addons/project_task_default_stage/models/__init__.py
odoo_addons/project_task_default_stage/models/project.py
odoo_addons/project_task_default_stage/static/description/icon.png
odoo_addons/project_task_default_stage/tests/__init__.py
odoo_addons/project_task_default_stage/tests/test_project_task_default_stage.py
odoo_addons/project_task_default_stage/views/project_view.xml
