Metadata-Version: 2.0
Name: odoo9-addon-project-task-default-stage
Version: 9.0.1.0.0.99.dev21
Summary: Recovery default task stage projects from v8
Home-page: UNKNOWN
Author: Incaser Informatica S.L., Odoo Community Association (OCA)
Author-email: support@odoo-community.org
License: AGPL-3
Platform: UNKNOWN
Classifier: Programming Language :: Python
Classifier: Framework :: Odoo
Classifier: License :: OSI Approved :: GNU Affero General Public License v3
Requires-Python: ~=2.7
Requires-Dist: odoo (<9.1a,>=9.0a)
